LICENSE
hypothesis_json/__init__.py
hypothesis_json/_utils.py
hypothesis_json/errors.py
hypothesis_json/py.typed
hypothesis_json/strategies.py
hypothesis_json/typing.py
hypothesis_json-2.0.1.dist-info/LICENSE
hypothesis_json-2.0.1.dist-info/WHEEL
hypothesis_json-2.0.1.dist-info/METADATA
hypothesis_json-2.0.1.dist-info/RECORD
