Metadata-Version: 2.1
Name: hypothesis-json
Version: 2.0.1
Summary: Hypothesis strategy to generate JSON
Home-page: https://github.com/macheins/hypothesis-json
License: UNKNOWN
Author: macheins
Requires-Python: >=3.5,<4.0
Classifier: Development Status :: 5 - Production/Stable
Classifier: Framework :: Hypothesis
Classifier: Intended Audience :: Developers
Classifier: License :: OSI Approved
Classifier: License :: OSI Approved :: MirOS License (MirOS)
Classifier: Programming Language :: Python :: 3
Classifier: Programming Language :: Python :: 3 :: Only
Classifier: Programming Language :: Python :: 3.5
Classifier: Programming Language :: Python :: 3.6
Classifier: Programming Language :: Python :: 3.7
Classifier: Topic :: Software Development :: Testing
Requires-Dist: hypothesis (>=4.0.2,<5.0.0)
Project-URL: Repository, https://github.com/macheins/hypothesis-json
